LICENSE.txt
MANIFEST.in
README.md
setup.cfg
setup.py
notebooks/UiO_66.DAT
notebooks/output_UiO_66.csv
notebooks/tutorial.ipynb
notebooks/.ipynb_checkpoints/tutorial-checkpoint.ipynb
nupxrd/__init__.py
nupxrd/nupxrd.py
nupxrd.egg-info/PKG-INFO
nupxrd.egg-info/SOURCES.txt
nupxrd.egg-info/dependency_links.txt
nupxrd.egg-info/top_level.txt