Metadata-Version: 1.1
Name: nupxrd
Version: 0.3.1
Summary: Extract raw data from a .dat file generated on the XRD                   equipment
Home-page: https://github.com/RossVerploegh/nupxrd/
Author: Ross Verploegh
Author-email: rverploe@alumni.nd.edu
License: MIT
Download-URL: https://github.com/RossVerploegh/nupxrd/archive/0.3.1                     .tar.gz
Keywords: powderXRD,MOF,NuMat
Platform: UNKNOWN
Classifier: Development Status :: 2 - Pre-Alpha
Classifier: Natural Language :: English
Classifier: Programming Language :: Python
Classifier: Programming Language :: Python :: 3
Classifier: Topic :: Scientific/Engineering :: Chemistry
